librarian_rag-0.1.1.dist-info/METADATA
librarian_rag-0.1.1.dist-info/RECORD
librarian_rag-0.1.1.dist-info/top_level.txt
librarian_rag-0.1.1.dist-info/WHEEL
librarian_rag-0.1.1.dist-info/LICENSE
librarian_rag.libs/libgcc_s-a0b57c20.so.1
librarian_rag.libs/libstdc++-0d31ccbe.so.6.0.32
librarian/__init__.py
librarian/utils.py
librarian/retriever/bm25s_retriever.py
librarian/retriever/elastic_retriever.py
librarian/retriever/typesense_retriever.py
librarian/retriever/__init__.py
librarian/retriever/dense_retriever.py
librarian/retriever/retriever_base.py
librarian/retriever/web_retrievers/web_reader.py
librarian/retriever/web_retrievers/web_retriever.py
librarian/retriever/web_retrievers/wikipedia_retriever.py
librarian/retriever/web_retrievers/__init__.py
librarian/retriever/web_retrievers/web_downloader.py
librarian/retriever/index/scann_index.py
librarian/retriever/index/faiss_index.py
librarian/retriever/index/annoy_index.py
librarian/retriever/index/__init__.py
librarian/retriever/index/index_base.py
librarian/models/sentence_transformers_model.py
librarian/models/model_base.py
librarian/models/__init__.py
librarian/models/hf_model.py
librarian/models/openai_model.py
librarian/models/utils.py
librarian/models/ollama_model.py
librarian/models/jina_model.py
librarian/models/anthropic_model.py
librarian/models/cohere_model.py
librarian/models/llamacpp_model.py
librarian/models/vllm_model.py
librarian/data/line_delimited_dataset.py
librarian/data/document_dataset.py
librarian/data/__init__.py
librarian/data/dataset.py
librarian/data/rag_dataset.py
librarian/data/chunking/chunker_base.py
librarian/data/chunking/__init__.py
librarian/data/chunking/basic_chunkers.py
librarian/data/text_process/basic_filters.py
librarian/data/text_process/normalize_tokens.py
librarian/data/text_process/processor.py
librarian/data/text_process/__init__.py
librarian/data/text_process/utils.py
librarian/data/text_process/pipeline.py
librarian/data/text_process/basic_processors.py
librarian/data/document_parser/docling_parser.py
librarian/data/document_parser/markitdown_parser.py
librarian/data/document_parser/__init__.py
