Metadata-Version: 2.1
Name: librarian-rag
Version: 0.1.1
Summary: A RAG Framework for Information Retrieval and Generation.
Home-page: https://github.com/ZhuochengZhang98/librarian
Author: Zhuocheng Zhang
Author-email: zhuocheng_zhang@outlook.com
License: MIT License
Classifier: Development Status :: 3 - Alpha
Classifier: Intended Audience :: Developers
Classifier: License :: OSI Approved :: MIT License
Classifier: Operating System :: OS Independent
Classifier: Programming Language :: Python :: 3
Classifier: Programming Language :: Python :: 3.11
Classifier: Programming Language :: Python :: 3.12
Classifier: Topic :: Scientific/Engineering :: Artificial Intelligence
Requires-Python: >=3.11
License-File: LICENSE
Requires-Dist: pandas
Requires-Dist: numpy<2.0.0
Requires-Dist: transformers>=4.44.0
Requires-Dist: tqdm
Requires-Dist: elasticsearch>=8.14.0
Requires-Dist: torch>=2.3.0
Requires-Dist: sacrebleu>=2.4.2
Requires-Dist: rouge
Requires-Dist: unidecode
Requires-Dist: openai>=1.30.1
Requires-Dist: tenacity
Requires-Dist: lancedb
Requires-Dist: lmdb
Requires-Dist: bm25s
Requires-Dist: hydra-core>=1.3
Requires-Dist: omegaconf>=2.3.0
Requires-Dist: pillow
Requires-Dist: accelerate>=0.26.0
Requires-Dist: faiss-cpu
Requires-Dist: beautifulsoup4
Provides-Extra: gui
Requires-Dist: gradio>=5.8.0; extra == "gui"
Provides-Extra: scann
Requires-Dist: scann>=1.3.2; extra == "scann"
Provides-Extra: llamacpp
Requires-Dist: llama_cpp_python>=0.2.84; extra == "llamacpp"
Provides-Extra: vllm
Requires-Dist: vllm>=0.5.0; extra == "vllm"
Provides-Extra: ollama
Requires-Dist: ollama>=0.2.1; extra == "ollama"
Provides-Extra: duckduckgo
Requires-Dist: duckduckgo_search>=6.1.6; extra == "duckduckgo"
Provides-Extra: anthropic
Requires-Dist: anthropic; extra == "anthropic"
Provides-Extra: minference
Requires-Dist: minference>=0.1.5; extra == "minference"
Provides-Extra: all
Requires-Dist: gradio>=5.8.0; extra == "all"
Requires-Dist: llama_cpp_python>=0.2.84; extra == "all"
Requires-Dist: vllm>=0.5.0; extra == "all"
Requires-Dist: ollama>=0.2.1; extra == "all"
Requires-Dist: duckduckgo_search>=6.1.6; extra == "all"
Requires-Dist: anthropic; extra == "all"
Requires-Dist: minference>=0.1.5; extra == "all"
Requires-Dist: PySocks>=1.7.1; extra == "all"
Provides-Extra: dev
Requires-Dist: black; extra == "dev"
Requires-Dist: pytest; extra == "dev"
